cfspopcon/__init__.py
cfspopcon/algorithm_class.py
cfspopcon/cli.py
cfspopcon/file_io.py
cfspopcon/formulas/__init__.py
cfspopcon/formulas/atomic_data/__init__.py
cfspopcon/formulas/atomic_data/atomic_data.py
cfspopcon/formulas/atomic_data/coeff_interpolator.py
cfspopcon/formulas/auxiliary_power/__init__.py
cfspopcon/formulas/auxiliary_power/auxiliary_power.py
cfspopcon/formulas/energy_confinement/__init__.py
cfspopcon/formulas/energy_confinement/energy_confinement_scalings.yaml
cfspopcon/formulas/energy_confinement/plasma_stored_energy.py
cfspopcon/formulas/energy_confinement/read_energy_confinement_scalings.py
cfspopcon/formulas/energy_confinement/solve_for_input_power.py
cfspopcon/formulas/energy_confinement/switch_confinement_scaling_on_threshold.py
cfspopcon/formulas/fusion_power/__init__.py
cfspopcon/formulas/fusion_power/average_fuel_ion_mass.py
cfspopcon/formulas/fusion_power/fusion_data.py
cfspopcon/formulas/fusion_power/fusion_gain.py
cfspopcon/formulas/fusion_power/fusion_rates.py
cfspopcon/formulas/geometry/__init__.py
cfspopcon/formulas/geometry/analytical.py
cfspopcon/formulas/geometry/volume_integral.py
cfspopcon/formulas/impurities/__init__.py
cfspopcon/formulas/impurities/core_radiator_conc.py
cfspopcon/formulas/impurities/edge_radiator_conc.py
cfspopcon/formulas/impurities/impurity_array_helpers.py
cfspopcon/formulas/impurities/impurity_charge_state.py
cfspopcon/formulas/impurities/set_up_impurity_concentration_array.py
cfspopcon/formulas/impurities/zeff_and_dilution_from_impurities.py
cfspopcon/formulas/metrics/__init__.py
cfspopcon/formulas/metrics/collisionality.py
cfspopcon/formulas/metrics/greenwald_density.py
cfspopcon/formulas/metrics/heat_exhaust_metrics.py
cfspopcon/formulas/metrics/larmor_radius.py
cfspopcon/formulas/plasma_current/__init__.py
cfspopcon/formulas/plasma_current/bootstrap_fraction.py
cfspopcon/formulas/plasma_current/flux_consumption/__init__.py
cfspopcon/formulas/plasma_current/flux_consumption/flux_consumption.py
cfspopcon-7.2.0.dist-info/LICENSE
cfspopcon-7.2.0.dist-info/METADATA
cfspopcon-7.2.0.dist-info/WHEEL
cfspopcon-7.2.0.dist-info/entry_points.txt
cfspopcon-7.2.0.dist-info/RECORD
