Metadata-Version: 2.3
Name: cfspopcon
Version: 7.2.0
Summary: Empirically-derived scoping of tokamak operational space.
Author: Commonwealth Fusion Systems
Requires-Python: >=3.10
Classifier: Development Status :: 5 - Production/Stable
Classifier: Intended Audience :: Science/Research
Classifier: License :: OSI Approved :: MIT License
Classifier: Programming Language :: Python :: 3
Classifier: Programming Language :: Python :: 3.10
Classifier: Programming Language :: Python :: 3.11
Classifier: Programming Language :: Python :: 3.12
Classifier: Programming Language :: Python :: 3.13
Classifier: Programming Language :: Python :: 3 :: Only
Classifier: Topic :: Scientific/Engineering :: Physics
Requires-Dist: click (>=8.1.0,<9.0.0)
Requires-Dist: contourpy (>=1.2.1,<2.0.0)
Requires-Dist: netcdf4 (>=1.7,<2.0)
Requires-Dist: numpy (>=2.2,<3.0) ; python_version < "3.11"
Requires-Dist: numpy (>=2.3,<3.0) ; python_version >= "3.11"
Requires-Dist: pandas (>=2.2,<3.0)
Requires-Dist: pint (>=0.24,<0.25)
Requires-Dist: pint-xarray (>=0.5,<0.6)
Requires-Dist: pyyaml (>=6.0,<7.0)
Requires-Dist: radas (>=2024.8.0)
Requires-Dist: scipy (>=1.8,<2.0)
Requires-Dist: seaborn (>=0.13,<0.14)
Requires-Dist: toml (>=0.10.2,<0.11.0)
Requires-Dist: typing-extensions (>=4.12,<5.0)
Requires-Dist: xarray (>=2024)
